lichess_client/__init__.py
lichess_client/abstract_endpoints/__init__.py
lichess_client/abstract_endpoints/abstract_account.py
lichess_client/abstract_endpoints/abstract_boards.py
lichess_client/abstract_endpoints/abstract_bots.py
lichess_client/abstract_endpoints/abstract_broadcast.py
lichess_client/abstract_endpoints/abstract_challenges.py
lichess_client/abstract_endpoints/abstract_chess_bot.py
lichess_client/abstract_endpoints/abstract_games.py
lichess_client/abstract_endpoints/abstract_messaging.py
lichess_client/abstract_endpoints/abstract_relations.py
lichess_client/abstract_endpoints/abstract_simulations.py
lichess_client/abstract_endpoints/abstract_studies.py
lichess_client/abstract_endpoints/abstract_teams.py
lichess_client/abstract_endpoints/abstract_tournaments.py
lichess_client/abstract_endpoints/abstract_users.py
lichess_client/clients/__init__.py
lichess_client/clients/abstract_client.py
lichess_client/clients/base_client.py
lichess_client/clients/client.py
lichess_client/endpoints/__init__.py
lichess_client/endpoints/account.py
lichess_client/endpoints/boards.py
lichess_client/endpoints/bots.py
lichess_client/endpoints/broadcast.py
lichess_client/endpoints/challenges.py
lichess_client/endpoints/chess_bot.py
lichess_client/endpoints/games.py
lichess_client/endpoints/messaging.py
lichess_client/endpoints/relations.py
lichess_client/endpoints/simulations.py
lichess_client/endpoints/studies.py
lichess_client/endpoints/teams.py
lichess_client/endpoints/tournaments.py
lichess_client/endpoints/users.py
lichess_client/helpers/__init__.py
lichess_client/helpers/response_helpers.py
lichess_client/utils/__init__.py
lichess_client/utils/client_errors.py
lichess_client/utils/enums.py
lichess_client/utils/hrefs.py
tests/unit/__init__.py
tests/unit/test_account_endpoint.py
tests/unit/test_base_client.py
tests/unit/test_boards_endpoint.py
tests/unit/test_bots_endpoint.py
tests/unit/test_broadcast_endpoint.py
tests/unit/test_challenges_endpoint.py
async_lichess_sdk-1.1.0.7.dist-info/LICENSE
async_lichess_sdk-1.1.0.7.dist-info/METADATA
async_lichess_sdk-1.1.0.7.dist-info/WHEEL
async_lichess_sdk-1.1.0.7.dist-info/top_level.txt
async_lichess_sdk-1.1.0.7.dist-info/RECORD
