Metadata-Version: 2.1
Name: async_lichess_sdk
Version: 1.1.0.7
Summary: Asynchronous Python API client for accessing the lichess.org API.
Home-page: https://github.com/amasend/lichees_python_SDK
Author: Amaedeusz Masny
Author-email: amadeuszmasny@gmail.com
License: Apache Software License
Platform: UNKNOWN
Classifier: Programming Language :: Python :: 3.6
Classifier: Programming Language :: Python :: 3.7
Classifier: License :: OSI Approved :: Apache Software License
Classifier: Operating System :: OS Independent
Requires-Python: >=3.6
